hypergz/VERSION
hypergz/__init__.py
hypergz/hypergraph_layout.py
hypergz/our_layout.py
hypergz/tests/__init__.py
hypergz/tests/our_running_examples.py
hypergz/tests/our_tests.py
hypergz-0.6.3.dist-info/METADATA
hypergz-0.6.3.dist-info/WHEEL
hypergz-0.6.3.dist-info/top_level.txt
hypergz-0.6.3.dist-info/RECORD
