Metadata-Version: 2.1
Name: hypergz
Version: 0.6.3
Summary: UNKNOWN
Home-page: https://github.com/AmitSheer/hypergz/
License: UNKNOWN
Project-URL: Documentation, https://github.com/AmitSheer/hypergz/
Project-URL: Bug Reports, https://github.com/AmitSheer/hypergz//issues
Project-URL: Source Code, https://github.com/AmitSheer/hypergz/
Platform: UNKNOWN
Classifier: Development Status :: 7 - Inactive
Classifier: Intended Audience :: Developers
Classifier: Topic :: Software Development :: Build Tools
Classifier: Programming Language :: Python :: 3
Classifier: Programming Language :: Python :: 3.9
Classifier: Programming Language :: Python :: 3 :: Only
Classifier: Operating System :: OS Independent
Requires-Python: >=3.8
Requires-Dist: networkx
Requires-Dist: numpy
Requires-Dist: scipy
